server/__init__.py
server/application.py
server/authentication.py
server/bootstrap.py
server/dispatcher.py
server/py.typed
server/template.py
gros_server-1.0.0.dist-info/LICENSE
gros_server-1.0.0.dist-info/METADATA
gros_server-1.0.0.dist-info/WHEEL
gros_server-1.0.0.dist-info/top_level.txt
gros_server-1.0.0.dist-info/RECORD
