Metadata-Version: 2.1
Name: gros-server
Version: 1.0.0
Summary: Grip on Software server framework
Author-email: Leon Helwerda <l.s.helwerda@liacs.leidenuniv.nl>
License: Apache 2.0
Project-URL: Homepage, https://gros.liacs.nl
Project-URL: PyPI, https://pypi.python.org/pypi/gros-server
Project-URL: Source Code, https://github.com/grip-on-software/server-framework
Project-URL: Issues, https://github.com/grip-on-software/server-framework/issues
Project-URL: Pull Requests, https://github.com/grip-on-software/server-framework/pulls
Project-URL: CI: GitHub Actions, https://github.com/grip-on-software/server-framework/actions
Project-URL: CI: Coveralls, https://coveralls.io/github/grip-on-software/server-framework?branch=master
Project-URL: CI: SonarCloud, https://sonarcloud.io/project/overview?id=grip-on-software_server-framework
Keywords: server framework,authentication,templates
Classifier: Development Status :: 5 - Production/Stable
Classifier: Environment :: Web Environment
Classifier: Intended Audience :: Developers
Classifier: Topic :: Internet :: WWW/HTTP :: HTTP Servers
Classifier: License :: OSI Approved :: Apache Software License
Classifier: Operating System :: OS Independent
Classifier: Programming Language :: Python :: 3
Classifier: Programming Language :: Python :: 3.8
Classifier: Programming Language :: Python :: 3.9
Classifier: Programming Language :: Python :: 3.10
Classifier: Programming Language :: Python :: 3.11
Classifier: Programming Language :: Python :: 3.12
Requires-Python: >=3.8
License-File: LICENSE
Requires-Dist: CherryPy ==18.9.0
Requires-Dist: flup ==1.0.3
Requires-Dist: gros-gatherer ==1.0.0
